blackduck_results/__init__.py
blackduck_results/cli.py
blackduck_results/findings.py
blackduck_results/projects.py
blackduck_results_test-1.0.23.dist-info/licenses/LICENSE
blackduck_results_test-1.0.23.dist-info/METADATA
blackduck_results_test-1.0.23.dist-info/WHEEL
blackduck_results_test-1.0.23.dist-info/entry_points.txt
blackduck_results_test-1.0.23.dist-info/top_level.txt
blackduck_results_test-1.0.23.dist-info/RECORD
