Metadata-Version: 2.4
Name: blackduck_results_test
Version: 1.0.23
Summary: Recursively traverse subprojects and report libraries with vulnerable components in a format suitable for integration with other tools and human consumption.
Home-page: https://https://adc.trendmicro.com/fabioa/blackduck-results
Author: Fabio Arciniegas
Author-email: fabio_arciniegas@trendmicro.com
Requires-Python: >=3.6
License-File: LICENSE
Requires-Dist: blackduck
Requires-Dist: pandas
Dynamic: author
Dynamic: author-email
Dynamic: description
Dynamic: description-content-type
Dynamic: home-page
Dynamic: license-file
Dynamic: requires-dist
Dynamic: requires-python
Dynamic: summary
